LICENSE
README.md
pyproject.toml
setup.py
./src/mod.c
src/pointers/__init__.py
src/pointers/_cstd.py
src/pointers/_pyapi.py
src/pointers/_utils.py
src/pointers/api_bindings.py
src/pointers/base_pointers.py
src/pointers/bindings.py
src/pointers/c_pointer.py
src/pointers/calloc.py
src/pointers/custom_binding.py
src/pointers/decay.py
src/pointers/exceptions.py
src/pointers/magic.py
src/pointers/malloc.py
src/pointers/object_pointer.py
src/pointers/stack_pointer.py
src/pointers/std_structs.py
src/pointers/structure.py
src/pointers/util.py
src/pointers/var_pointer.py
src/pointers_clone.py.egg-info/PKG-INFO
src/pointers_clone.py.egg-info/SOURCES.txt
src/pointers_clone.py.egg-info/dependency_links.txt
src/pointers_clone.py.egg-info/requires.txt
src/pointers_clone.py.egg-info/top_level.txt
tests/test_allocation.py
tests/test_bindings.py
tests/test_decay.py
tests/test_pointer.py
tests/test_var_pointer.py