Metadata-Version: 2.1
Name: pointers-clone.py
Version: 0.0.0
Summary: Bringing the hell of pointers to Python.
Author-email: ZeroIntensity <zintensitydev@gmail.com>
License: MIT
Project-URL: Documentation, https://pointers.zintensity.dev
Project-URL: Issues, https://github.com/ZeroIntensity/pointers.py/issues
Project-URL: Source, https://github.com/ZeroIntensity/pointers.py
Keywords: python,pointers
Classifier: Programming Language :: Python
Classifier: Programming Language :: Python :: 3.6
Classifier: Programming Language :: Python :: 3.7
Classifier: Programming Language :: Python :: 3.8
Classifier: Programming Language :: Python :: 3.9
Classifier: Programming Language :: Python :: 3.10
Classifier: Programming Language :: Python :: Implementation :: CPython
Requires-Python: >=3.6
License-File: LICENSE
